CHANGELOG.txt
INFO.txt
LICENSE.txt
MANIFEST.in
README.txt
setup.py
FML/Graphics.py
FML/Window.py
FML/__init__.py
FMLEngine.egg-info/PKG-INFO
FMLEngine.egg-info/SOURCES.txt
FMLEngine.egg-info/dependency_links.txt
FMLEngine.egg-info/requires.txt
FMLEngine.egg-info/top_level.txt
test/test.py