Metadata-Version: 2.1
Name: FMLEngine
Version: 0.0.5
Summary: Pre-Apha Graphics Engine
Home-page: UNKNOWN
Author: Josh
Author-email: kingcode102@gmail.com
License: MIT
Keywords: Graphics Engine
Platform: UNKNOWN
Classifier: Development Status :: 5 - Production/Stable
Classifier: Intended Audience :: Developers
Classifier: Operating System :: Microsoft :: Windows :: Windows 10
Classifier: License :: OSI Approved :: MIT License
Classifier: Programming Language :: Python :: 3
License-File: LICENSE.txt
